Metadata-Version: 1.1
Name: django-logger
Version: 0.1.1.0
Summary: django_logger
Home-page: UNKNOWN
Author: ChaosHead
Author-email: prostomrkot@gmail.com
License: MIT License
Keywords: django
Platform: UNKNOWN
Classifier: Environment :: Web Environment
Classifier: Framework :: Django
Classifier: Intended Audience :: Developers
Classifier: Programming Language :: Python
Requires: python (>= 2.5)
Requires: django (>= 1.3)
